releasenote/__init__.py
releasenote/git.py
releasenote/mingle.py
releasenote/parser.py
releasenote-1.0.dist-info/DESCRIPTION.rst
releasenote-1.0.dist-info/METADATA
releasenote-1.0.dist-info/RECORD
releasenote-1.0.dist-info/WHEEL
releasenote-1.0.dist-info/entry_points.txt
releasenote-1.0.dist-info/metadata.json
releasenote-1.0.dist-info/top_level.txt
